Workbook

Sheet Dashboard
B2: Construction Profit Intelligence Dashboard
B3: Portfolio demo — Canadian market context (Statistics Canada) + illustrative operational data. See 'Notes & Sources'.
B5: TOTAL CONTRACT VALUE | D5: TOTAL ACTUAL COST | F5: GROSS PROFIT MARGIN | H5: COST VARIANCE | J5: PROJECTS AT RISK | L5: AVG BID MARGIN IMPACT
B6: ='Project Data'!B12 -> 17670000 | D6: ='Project Data'!D12 -> 15000000 | F6: ='Project Data'!G12 -> 0.15110357 | H6: ='Project Data'!F12 -> 0.034482759 | J6: ='Project Data'!B18 -> 2 | L6: ='Bid Simulator'!B15 -> 0.047619048

Sheet Project Data
B2: Project Data
B3: Editable inputs = blue. Formulas = black. Update Contract/Budget/Actual to refresh the whole workbook.
A5: Project | B5: Contract Value | C5: Budgeted Cost | D5: Actual Cost | E5: Cost Variance $ | F5: Cost Variance % | G5: Margin % | H5: Status
A6: Downtown Tower Renovation | B6: 2620000 | C6: 2100000 | D6: 2250000 | E6: =D6-C6 -> 150000 | F6: =IF(C6=0,0,E6/C6) -> 0.071428571 | G6: =IF(B6=0,0,(B6-D6)/B6) -> 0.14122137 | H6: =IF(G6<0.15,"At Risk",IF(G6<0.18,"Watch","Good")) -> At Risk
A7: Riverside Office Fit-out | B7: 925000 | C7: 800000 | D7: 720000 | E7: =D7-C7 -> -80000 | F7: =IF(C7=0,0,E7/C7) -> -0.1 | G7: =IF(B7=0,0,(B7-D7)/B7) -> 0.22162162 | H7: =IF(G7<0.15,"At Risk",IF(G7<0.18,"Watch","Good")) -> Good
A8: Maple Residential Build | B8: 3690000 | C8: 3000000 | D8: 3100000 | E8: =D8-C8 -> 100000 | F8: =IF(C8=0,0,E8/C8) -> 0.033333333 | G8: =IF(B8=0,0,(B8-D8)/B8) -> 0.1598916 | H8: =IF(G8<0.15,"At Risk",IF(G8<0.18,"Watch","Good")) -> Watch
A9: Northgate Industrial Shell | B9: 1965000 | C9: 1650000 | D9: 1590000 | E9: =D9-C9 -> -60000 | F9: =IF(C9=0,0,E9/C9) -> -0.036363636 | G9: =IF(B9=0,0,(B9-D9)/B9) -> 0.19083969 | H9: =IF(G9<0.15,"At Risk",IF(G9<0.18,"Watch","Good")) -> Good
A10: Harbourview Institutional | B10: 5110000 | C10: 4200000 | D10: 4550000 | E10: =D10-C10 -> 350000 | F10: =IF(C10=0,0,E10/C10) -> 0.083333333 | G10: =IF(B10=0,0,(B10-D10)/B10) -> 0.10958904 | H10: =IF(G10<0.15,"At Risk",IF(G10<0.18,"Watch","Good")) -> At Risk
A11: Sunridge Multi-family | B11: 3360000 | C11: 2750000 | D11: 2790000 | E11: =D11-C11 -> 40000 | F11: =IF(C11=0,0,E11/C11) -> 0.014545455 | G11: =IF(B11=0,0,(B11-D11)/B11) -> 0.16964286 | H11: =IF(G11<0.15,"At Risk",IF(G11<0.18,"Watch","Good")) -> Watch
A12: TOTAL / PORTFOLIO | B12: =SUM(B6:B11) -> 17670000 | C12: =SUM(C6:C11) -> 14500000 | D12: =SUM(D6:D11) -> 15000000 | E12: =D12-C12 -> 500000 | F12: =IF(C12=0,0,E12/C12) -> 0.034482759 | G12: =IF(B12=0,0,(B12-D12)/B12) -> 0.15110357
A15: Status Summary
A16: Good | B16: =COUNTIF(H6:H11,A16) -> 2
A17: Watch | B17: =COUNTIF(H6:H11,A17) -> 2
A18: At Risk | B18: =COUNTIF(H6:H11,A18) -> 2
A21: Assumptions: Contract Value, Budgeted Cost and Actual Cost are illustrative sample figures for this demo portfolio (not a real company's financials). Status thresholds: Margin <15% = At Risk, 15–18% = Watch, >=18% = Good.

Sheet Cost Variance
B2: Cost Variance Analysis
B3: Budgeted vs actual cost by category. Drives the margin-impact figure on the Dashboard.
A5: Category | B5: Budgeted $ | C5: Actual $ | D5: Variance $ | E5: Variance %
A6: Materials | B6: 2400000 | C6: 2688000 | D6: =C6-B6 -> 288000 | E6: =IF(B6=0,0,D6/B6) -> 0.12
A7: Labour | B7: 1900000 | C7: 2052000 | D7: =C7-B7 -> 152000 | E7: =IF(B7=0,0,D7/B7) -> 0.08
A8: Equipment | B8: 770000 | C8: 800800 | D8: =C8-B8 -> 30800 | E8: =IF(B8=0,0,D8/B8) -> 0.04
A9: Subcontractors | B9: 680000 | C9: 720800 | D9: =C9-B9 -> 40800 | E9: =IF(B9=0,0,D9/B9) -> 0.06
A10: TOTAL | B10: =SUM(B6:B9) -> 5750000 | C10: =SUM(C6:C9) -> 6261600 | D10: =SUM(D6:D9) -> 511600 | E10: =IF(B10=0,0,D10/B10) -> 0.088973913
A12: Cost overrun of this magnitude, concentrated in materials, is the leading driver of the portfolio's margin gap versus original bids. Category % increases reflect reported 2025-2026 input-cost pressure (steel tariffs, skilled-labour shortages); dollar figures are illustrative for this sample portfolio.

Sheet Workforce
B2: Workforce Efficiency
B3: Planned vs actual labour hours, current quarter (illustrative sample data).
A5: Week | B5: Planned Hours | C5: Actual Hours | D5: Variance % | F5: Metric | G5: Value
A6: Wk 1 | B6: 3300 | C6: 3333 | D6: =IF(B6=0,0,(C6-B6)/B6) -> 0.01 | F6: Budgeted cost / hour | G6: 49
A7: Wk 2 | B7: 3300 | C7: 3267 | D7: =IF(B7=0,0,(C7-B7)/B7) -> -0.01 | F7: Actual cost / hour | G7: 54
A8: Wk 3 | B8: 3300 | C8: 3201 | D8: =IF(B8=0,0,(C8-B8)/B8) -> -0.03 | F8: Cost / hour variance | G8: =IF(G6=0,0,(G7-G6)/G6) -> 0.10204082
A9: Wk 4 | B9: 3300 | C9: 3135 | D9: =IF(B9=0,0,(C9-B9)/B9) -> -0.05 | F9: Overtime hours (sample) | G9: 2760
A10: Wk 5 | B10: 3300 | C10: 3069 | D10: =IF(B10=0,0,(C10-B10)/B10) -> -0.07 | F10: Overtime % of actual hours | G10: =IF(C12=0,0,G9/C12) -> 0.14495037
A11: Wk 6 | B11: 3300 | C11: 3036 | D11: =IF(B11=0,0,(C11-B11)/B11) -> -0.08 | F11: Overtime target | G11: 0.1
A12: TOTAL | B12: =SUM(B6:B11) -> 19800 | C12: =SUM(C6:C11) -> 19041 | D12: =IF(B12=0,0,(C12-B12)/B12) -> -0.038333333
A14: Overtime running above the 10% target and cost-per-hour up versus budget point to crew-scheduling review ahead of the next bid cycle. All figures are illustrative sample data.
A15: Week | B15: Index (Wk1=101)
A16: Wk 1 | B16: 101
A17: Wk 2 | B17: 99
A18: Wk 3 | B18: 97
A19: Wk 4 | B19: 95
A20: Wk 5 | B20: 93
A21: Wk 6 | B21: 92

Sheet Bid Simulator
B2: Bid Decision Simulator
B3: Change the yellow cell (steel/material cost increase %) and every output recalculates live.
A6: Contract value | B6: 5000000
A7: Estimated cost (base bid) | B7: 4200000
A8: Baseline margin | B8: =(B6-B7)/B6 -> 0.16
A9: Cost impact per 1% material increase | B9: 20000
A10: Steel / material cost increase % | B10: 0.1
A11: New projected cost | B11: =B7+(B10*100*B9) -> 4400000
A12: New projected margin | B12: =(B6-B11)/B6 -> 0.12
A13: Margin drop (points) | B13: =(B8-B12)*100 -> 4
A14: Contract value needed to protect baseline margin | B14: =B11/(1-B8) -> 5238095.2
A15: Recommended bid increase % | B15: =IF(B14<=B6,0,(B14-B6)/B6) -> 0.047619048
A17: Recommendation
A18: =IF(B13<1,"Bid remains healthy - no action needed.",IF(B13<=3,"Monitor closely - consider a 2-3% contingency on remaining spend.","Increase bid price by "&TEXT(B15,"0.0%")&" to protect target margin.")) -> Increase bid price by 4.8% to protect target margin.
A20: Model: additional cost = (steel/material increase %) x (cost impact per 1% assumption). Calibrated so a 10% steel cost increase moves margin from 16.0% to 12.0% - consistent with the example used to size the cost-impact assumption. Contract value and base cost are illustrative.

Sheet Market Data
B2: Market Data (External)
B3: Statistics Canada — Building Construction Price Index & Building Permits. Reference only; not company data.
A5: Quarter | B5: Residential BCPI | C5: Non-Residential BCPI
A6: Q3 '25 | B6: 102.1 | C6: 103
A7: Q4 '25 | B7: 102.8 | C7: 104.1
A8: Q1 '26 | B8: 103.5 | C8: 105
A9: Q2 '26 | B9: 104 | C9: 106.5
A11: Source: Statistics Canada, Building Construction Price Indexes (The Daily). Q1-Q2 2026 quarterly % changes as reported; base 2023=100, earlier quarters modeled for trend continuity.
A14: Region | B14: Permit Value Growth 2024→2025
A15: Atlantic | B15: 0.168
A16: Prairie | B16: 0.147
A17: Ontario | B17: 0.061
A18: Quebec | B18: 0.043
A19: B.C. | B19: 0.03
A21: Source: Statistics Canada, Building Permits by province/region. Atlantic and Prairie figures as reported (fastest-growing markets); Ontario/Quebec/B.C. modeled from monthly permit-value releases for comparison.

Sheet Notes & Sources
B2: Notes & Data Sources
B3: Read this before presenting the workbook.
A5: External Market Data
A6: Statistics Canada | B6: Building Construction Price Indexes (BCPI) - residential & non-residential, quarterly.
A7: Statistics Canada | B7: Building Permits - value by province/region.
A9: Demo Operational Data (illustrative)
A10: Project Data | B10: Contract values, budgeted/actual costs and margins - sample portfolio, not a real company's books.
A11: Cost Variance | B11: Category budgets/actuals - illustrative, calibrated to reported 2025-2026 cost-pressure ranges.
A12: Workforce | B12: Labour hours, cost/hour and productivity index - illustrative sample data.
A13: Bid Simulator | B13: Contract/cost assumptions and cost-impact-per-1% figure - illustrative; freely editable.
A15: How to use this workbook
A16: Project Data / Cost Variance / Workforce | B16: Blue cells are inputs - overwrite with real figures and every formula, conditional format and chart on the Dashboard updates automatically.
A17: Bid Simulator | B17: Change the yellow lever cell (steel/material cost increase %) to stress-test a bid before signing.
A18: Dashboard | B18: Pulls only from formulas on the other tabs - never edit it directly.
